gamepad_video_controller/__init__.py
gamepad_video_controller/main.py
gamepad_video_controller-0.1.1.dist-info/licenses/LICENSE
gamepad_video_controller-0.1.1.dist-info/METADATA
gamepad_video_controller-0.1.1.dist-info/WHEEL
gamepad_video_controller-0.1.1.dist-info/entry_points.txt
gamepad_video_controller-0.1.1.dist-info/top_level.txt
gamepad_video_controller-0.1.1.dist-info/RECORD
