Metadata-Version: 2.4
Name: gamepad-video-controller
Version: 0.1.1
Summary: Control video players and browsers using a gamepad
Author: Samriddha Chattopadhyay
License: MIT
Requires-Python: >=3.11
License-File: LICENSE
Requires-Dist: pygame>=2.6.1
Requires-Dist: pynput>=1.8.1
Dynamic: license-file
